influx_si_data_manager/__init__.py
influx_si_data_manager/__main__.py
influx_si_data_manager/test_data/isocor_results.tabular
influx_si_data_manager/test_data/mapping.txt
influx_si_data_manager/test_data/summary.csv
influx_si_data_manager/utils/__init__.py
influx_si_data_manager/utils/isocor2mtf.py
influx_si_data_manager/utils/map_data.py
influx_si_data_manager/utils/physiofit2mtf.py
influx_si_data_manager-1.1.1.dist-info/entry_points.txt
influx_si_data_manager-1.1.1.dist-info/LICENSE
influx_si_data_manager-1.1.1.dist-info/METADATA
influx_si_data_manager-1.1.1.dist-info/WHEEL
influx_si_data_manager-1.1.1.dist-info/RECORD
