Metadata-Version: 2.1
Name: influx-si-data-manager
Version: 1.1.1
Summary: Data manager for handling influx_si inputs on Workflow4Metabolomics (usegalaxy.org)
License: GNU General Public License (GPL)
Author: legregam
Author-email: legregam@insa-toulouse.fr
Requires-Python: >=3.9,<4.0
Classifier: License :: Other/Proprietary License
Classifier: Programming Language :: Python :: 3
Classifier: Programming Language :: Python :: 3.9
Classifier: Programming Language :: Python :: 3.10
Classifier: Programming Language :: Python :: 3.11
Classifier: Programming Language :: Python :: 3.12
Classifier: Programming Language :: Python :: 3.13
Requires-Dist: pandas (>=2.0.1,<3.0.0)
